slicker/__init__.py
slicker/cleanup.py
slicker/inputs.py
slicker/khodemod.py
slicker/model.py
slicker/moves.py
slicker/removal.py
slicker/replacement.py
slicker/slicker.py
slicker/unicode_util.py
slicker/util.py
slicker-0.9.3.dist-info/METADATA
slicker-0.9.3.dist-info/RECORD
slicker-0.9.3.dist-info/WHEEL
slicker-0.9.3.dist-info/entry_points.txt
slicker-0.9.3.dist-info/top_level.txt
