Metadata-Version: 2.1
Name: slicker
Version: 0.9.3
Summary: A tool for moving python files.
Home-page: https://github.com/Khan/slicker
Author: Khan Academy
Author-email: opensource+pypi@khanacademy.org
License: UNKNOWN
Keywords: codemod,refactor,refactoring
Platform: UNKNOWN
Classifier: License :: OSI Approved :: MIT License
Classifier: Programming Language :: Python :: 2
Classifier: Programming Language :: Python :: 2.7
Requires-Dist: asttokens (==1.1.8)
Requires-Dist: tqdm (==4.19.5)
Requires-Dist: fix-includes (==0.2)
